colego/__init__.py
colego-0.0.1.dist-info/LICENSE.txt
colego-0.0.1.dist-info/METADATA
colego-0.0.1.dist-info/WHEEL
colego-0.0.1.dist-info/top_level.txt
colego-0.0.1.dist-info/RECORD
