Metadata-Version: 2.1
Name: colego
Version: 0.0.1
Summary: Simple package that converts a text to have colors in a terminal output.
Home-page: UNKNOWN
Author: Hastaluego
Author-email: superduperst3ve@gmail.com
License: MIT
Keywords: color,colour,terminal,output,text,colored,coloured
Platform: UNKNOWN
Classifier: Development Status :: 5 - Production/Stable
Classifier: Intended Audience :: Education
Classifier: Operating System :: Microsoft :: Windows :: Windows 10
Classifier: License :: OSI Approved :: MIT License
Classifier: Programming Language :: Python :: 3
License-File: LICENSE.txt
